videojungle/__init__.py
videojungle/client.py
videojungle/model.py
videojungle/utils.py
videojungle-0.1.80.dist-info/METADATA
videojungle-0.1.80.dist-info/WHEEL
videojungle-0.1.80.dist-info/top_level.txt
videojungle-0.1.80.dist-info/RECORD
