Metadata-Version: 2.4
Name: videojungle
Version: 0.1.80
Summary: A Python client for the Video Jungle API
Project-URL: repository, https://github.com/burningion/video-jungle-python
Classifier: Programming Language :: Python :: 3
Classifier: License :: OSI Approved :: MIT License
Classifier: Operating System :: OS Independent
Requires-Python: >=3.8
Requires-Dist: requests
Requires-Dist: pydantic
Requires-Dist: httpx
